b_class_worth/__init__.py
b_class_worth/main.py
worth_calculator_mcp/__init__.py
worth_calculator_mcp/main.py
b_class_worth-0.1.0.dist-info/METADATA
b_class_worth-0.1.0.dist-info/WHEEL
b_class_worth-0.1.0.dist-info/entry_points.txt
b_class_worth-0.1.0.dist-info/top_level.txt
b_class_worth-0.1.0.dist-info/RECORD
